MANIFEST.in
README.md
setup.cfg
setup.py
customers/__init__.py
customers/admin.py
customers/forms.py
customers/models.py
customers/urls.py
customers/views.py
customers/locale/uk/LC_MESSAGES/django.mo
customers/locale/uk/LC_MESSAGES/django.po
customers/migrations/0001_initial.py
customers/migrations/0002_customer_discount.py
customers/migrations/__init__.py
customers/templates/customers/actions_cell.html
customers/templates/customers/detail.html
customers/templates/customers/sale_count_cell.html
django_mp_vehicle_customers.egg-info/PKG-INFO
django_mp_vehicle_customers.egg-info/SOURCES.txt
django_mp_vehicle_customers.egg-info/dependency_links.txt
django_mp_vehicle_customers.egg-info/top_level.txt