Metadata-Version: 2.1
Name: django-mp-vehicle-customers
Version: 1.0.0
Summary: Django customers app
Home-page: https://github.com/pmaigutyak/mp-vehicle-customers
Author: Paul Maigutyak
Author-email: pmaigutyak@gmail.com
License: MIT
Download-URL: https://github.com/pmaigutyak/mp-vehicle-customers/archive/1.0.0.tar.gz
Platform: UNKNOWN
